myportfolio/__init__.py
myportfolio/models.py
myportfolio/services.py
myportfolio/types.py
myportfolio/utils.py
myportfolio-0.6.0.dist-info/METADATA
myportfolio-0.6.0.dist-info/WHEEL
myportfolio-0.6.0.dist-info/licenses/LICENSE
myportfolio-0.6.0.dist-info/RECORD
