Metadata-Version: 2.4
Name: myportfolio
Version: 0.6.0
Summary: 
License-File: LICENSE
Author: aan
Author-email: andoludovic.andriamamonjy@gmail.com
Requires-Python: >=3.11,<3.13
Classifier: Programming Language :: Python :: 3
Classifier: Programming Language :: Python :: 3.11
Classifier: Programming Language :: Python :: 3.12
Requires-Dist: PyPortfolioOpt (>=1.5.6,<2.0.0)
Requires-Dist: bearishpy (>=0.41.0,<1.0.0)
Requires-Dist: scikit-learn (>=1.7.2,<2.0.0)
